mh_logtools/constants.py
mh_logtools/logger.py
mh_logtools-0.1.3.dist-info/METADATA
mh_logtools-0.1.3.dist-info/WHEEL
mh_logtools-0.1.3.dist-info/RECORD
